{"Bedroom": {"Size": [-230, -150, 460, 300], "Furnitures": {"Bed": {"Size": [[-230, -120, 180, 210]]}, "Nightstand": {"Size": [[-50, -120, 40, 40]]}, "Wardrobe": {"Size": [[140, 50, 60, 100]]}}}, "Kitchen": {"Size": [-230, -390, 460, 240], "Furnitures": {"Kitchen_Stove": {"Size": [[-230, -390, 120, 60]]}, "Cupboard": {"Size": [[150, -390, 50, 150]]}, "Refrigerator": {"Size": [[-230, -240, 60, 60]]}, "Wash_Machine": {"Size": [[-10, -390, 60, 60]]}}}, "Livingroom": {"Size": [230, -390, 360, 660], "Furnitures": {"Dinner_Table": {"Size": [[420, -380, 80, 140]]}, "Chair": {"Size": [[440, -230, 40, 40], [370, -330, 40, 40]]}, "Sofa": {"Size": [[290, -115, 80, 190]]}, "TV": {"Size": [[530, -70, 60, 100]]}}, "Toilet": {"Size": [320, 150, 90, 120]}, "Bathroom": {"Size": [410, 150, 180, 120]}}, "Doors": {"Entrance": {"Size": [590, -360, 0, 60]}, "Toilet_Door": {"Size": [335, 150, 60, 0]}, "Bathroom_Door": {"Size": [470, 150, 60, 0]}}, "Walls": [[[-230, -390], [-230, 150]], [[230, 150], [230, 270]], [[590, -390], [590, 150]], [[-230, 150], [230, 150]], [[230, 270], [320, 270]], [[-230, -390], [590, -390]]], "Boundary": [[-230, 590], [-390, 270]]}