{"Bedroom": {"Size": [-150, -150, 300, 300], "Furnitures": {"Bed": {"Size": [[-150, -150, 180, 210]]}, "Wardrobe": {"Size": [[90, -15, 60, 60]]}}}, "Kitchen": {"Size": [-150, 670, 180, 340], "Furnitures": {"Kitchen_Stove": {"Size": [[-30, 950, 60, 60]]}, "Cupboard": {"Size": [[-150, 700, 120, 50]]}, "Refrigerator": {"Size": [[-150, 880, 60, 60]]}, "Trash_Bin": {"Size": [[0, 810, 30, 30]]}}}, "Livingroom": {"Size": [-150, 150, 300, 520], "Furnitures": {"Sofa": {"Size": [[-150, 400, 140, 80]]}, "TV": {"Size": [[-120, 180, 80, 40]]}}, "Toilet": {"Size": [150, 330, 120, 90]}, "Bathroom": {"Size": [150, 150, 120, 180]}}, "Doors": {"Entrance": {"Size": [60, -150, 60, 0]}, "Toilet_Door": {"Size": [150, 345, 0, 60]}, "Bathroom_Door": {"Size": [150, 210, 0, 60]}}, "Walls": [[[-150, -150], [-150, 1010]], [[150, -150], [150, 150]], [[30, 670], [30, 1010]], [[150, 420], [150, 670]], [[-150, -150], [150, -150]], [[-150, 1010], [30, 1010]], [[30, 670], [150, 670]]], "Boundary": [[-150, 270], [-150, 1010]]}