{"Bedroom": {"Size": [-180, -120, 360, 240], "Furnitures": {"Bed": {"Size": [[30, -120, 150, 210]]}, "Wardrobe": {"Size": [[-90, -120, 60, 60]]}}}, "Kitchen": {"Size": [-60, 520, 240, 280], "Furnitures": {"Kitchen_Stove": {"Size": [[-60, 740, 60, 60]]}, "Cupboard": {"Size": [[80, 650, 100, 50]]}, "Refrigerator": {"Size": [[-60, 585, 60, 60]]}, "Trash_Bin": {"Size": [[150, 770, 30, 30]]}}}, "Livingroom": {"Size": [-180, 120, 360, 400], "Furnitures": {"Dinner_Table": {"Size": [[-170, 410, 80, 80]]}, "Chair": {"Size": [[-150, 360, 40, 40]]}, "Sofa": {"Size": [[40, 210, 80, 90]]}, "TV": {"Size": [[-180, 225, 40, 60]]}}, "Toilet": {"Size": [180, 250, 120, 90]}, "Bathroom": {"Size": [180, 340, 120, 180]}}, "Doors": {"Entrance": {"Size": [180, 160, 0, 60]}, "Toilet_Door": {"Size": [180, 265, 0, 60]}, "Bathroom_Door": {"Size": [180, 400, 0, 60]}}, "Walls": [[[-60, 520], [-60, 800]], [[-180, -120], [-180, 520]], [[180, 520], [180, 800]], [[180, -120], [180, 250]], [[-180, -120], [180, -120]], [[-60, 800], [180, 800]], [[-180, 520], [-60, 520]]], "Boundary": [[-180, 300], [-120, 800]]}