{"Bedroom": {"Size": [-220, -140, 440, 280], "Furnitures": {"Bed": {"Size": [[-75, -140, 210, 180]]}}, "Bathroom": {"Size": [-340, -40, 120, 180]}}, "Kitchen": {"Size": [-100, 620, 320, 300], "Furnitures": {"Kitchen_Stove": {"Size": [[-100, 860, 60, 60]]}, "Cupboard": {"Size": [[70, 870, 150, 50]]}, "Refrigerator": {"Size": [[160, 650, 60, 60]]}, "Wash_Machine": {"Size": [[-100, 695, 60, 60]]}}}, "Livingroom": {"Size": [-220, 140, 440, 480], "Furnitures": {"Sofa": {"Size": [[0, 420, 80, 140]]}, "TV": {"Size": [[-220, 450, 40, 80]]}, "Dinner_Table": {"Size": [[30, 200, 160, 80]]}, "Chair": {"Size": [[-20, 220, 40, 40], [90, 290, 40, 40], [90, 150, 40, 40]]}}, "Toilet": {"Size": [-340, 140, 120, 90]}}, "Doors": {"Entrance": {"Size": [-190, 620, 60, 0]}, "Toilet_Door": {"Size": [-220, 155, 0, 60]}, "Bathroom_Door": {"Size": [-220, 20, 0, 60]}}, "Walls": [[[220, -140], [220, 920]], [[-220, -140], [-220, -40]], [[-100, 620], [-100, 920]], [[-220, 230], [-220, 620]], [[-220, -140], [220, -140]], [[-100, 920], [220, 920]], [[-220, 620], [-100, 620]]], "Boundary": [[-340, 220], [-140, 920]]}