{"Bedroom": {"Size": [-190, -190, 380, 380], "Furnitures": {"Bed": {"Size": [[-120, -190, 210, 180]]}, "Wardrobe": {"Size": [[-190, 60, 120, 60]]}}}, "Kitchen": {"Size": [190, -190, 280, 380], "Furnitures": {"Kitchen_Stove": {"Size": [[290, -20, 180, 60]]}, "Cupboard": {"Size": [[350, -190, 120, 50]]}, "Refrigerator": {"Size": [[220, -190, 60, 60]]}}, "Toilet": {"Size": [470, 100, 120, 90]}}, "Livingroom": {"Size": [-70, 190, 540, 420], "Furnitures": {"Dinner_Table": {"Size": [[-10, 520, 160, 80]]}, "Chair": {"Size": [[-60, 540, 40, 40], [50, 470, 40, 40], [160, 540, 40, 40]]}}, "Bathroom": {"Size": [470, 190, 120, 180]}}, "Doors": {"Entrance": {"Size": [-160, 190, 60, 0]}, "Toilet_Door": {"Size": [470, 115, 0, 60]}, "Bathroom_Door": {"Size": [470, 250, 0, 60]}}, "Walls": [[[-190, -190], [470, -190]], [[-190, 190], [-70, 190]], [[-70, 610], [470, 610]], [[-190, -190], [-190, 190]], [[-70, 190], [-70, 610]], [[470, -190], [470, 100]], [[470, 370], [470, 610]]], "Boundary": [[-190, 590], [-190, 610]]}