{"Bedroom": {"Size": [-270, -140, 540, 280], "Furnitures": {"Bed": {"Size": [[-240, -70, 150, 210]]}, "Nightstand": {"Size": [[-90, 100, 40, 40]]}, "Wardrobe": {"Size": [[150, -30, 120, 60]]}}}, "Kitchen": {"Size": [-270, -400, 420, 260], "Furnitures": {"Kitchen_Stove": {"Size": [[-270, -400, 120, 60]]}, "Cupboard": {"Size": [[0, -220, 150, 50]]}, "Refrigerator": {"Size": [[90, -340, 60, 60]]}, "Wash_Machine": {"Size": [[-60, -400, 60, 60]]}}}, "Livingroom": {"Size": [-670, -380, 400, 520], "Furnitures": {"Dinner_Table": {"Size": [[-400, -40, 80, 140]]}, "Chair": {"Size": [[-310, 10, 40, 40], [-380, -90, 40, 40], [-450, 10, 40, 40]]}, "Sofa": {"Size": [[-670, -160, 140, 80]]}, "TV": {"Size": [[-640, 100, 80, 40]]}}, "Toilet": {"Size": [-540, -380, 90, 120]}, "Bathroom": {"Size": [-450, -380, 180, 120]}}, "Doors": {"Entrance": {"Size": [-630, -380, 60, 0]}, "Toilet_Door": {"Size": [-525, -260, 60, 0]}, "Bathroom_Door": {"Size": [-390, -260, 60, 0]}}, "Walls": [[[270, -140], [270, 140]], [[150, -400], [150, -140]], [[-270, -400], [-270, -380]], [[-670, -380], [-670, 140]], [[-670, 140], [270, 140]], [[150, -140], [270, -140]], [[-270, -400], [150, -400]], [[-670, -380], [-540, -380]]], "Boundary": [[-670, 270], [-400, 140]]}