{"Bedroom": {"Size": [-260, -140, 520, 280], "Furnitures": {"Bed": {"Size": [[-130, -40, 210, 180]]}, "Wardrobe": {"Size": [[-260, -20, 60, 100]]}}, "Bathroom": {"Size": [140, -140, 120, 180]}}, "Kitchen": {"Size": [-140, -420, 400, 280], "Furnitures": {"Kitchen_Stove": {"Size": [[-140, -390, 120, 60]]}, "Cupboard": {"Size": [[-140, -220, 150, 50]]}, "Refrigerator": {"Size": [[200, -370, 60, 60]]}}, "Toilet": {"Size": [140, -230, 120, 90]}}, "Livingroom": {"Size": [-260, -800, 520, 380], "Furnitures": {"Sofa": {"Size": [[-260, -580, 140, 80]]}, "TV": {"Size": [[-240, -800, 100, 40]]}, "Dinner_Table": {"Size": [[90, -665, 160, 80]]}, "Chair": {"Size": [[40, -645, 40, 40], [150, -715, 40, 40], [150, -575, 40, 40]]}}}, "Doors": {"Entrance": {"Size": [-230, -140, 60, 0]}, "Toilet_Door": {"Size": [140, -215, 0, 60]}, "Bathroom_Door": {"Size": [140, -80, 0, 60]}}, "Walls": [[[-260, -140], [-260, 140]], [[-140, -420], [-140, -140]], [[-260, -800], [-260, -420]], [[260, 40], [260, 140]], [[260, -800], [260, -230]], [[-260, 140], [260, 140]], [[-260, -420], [-140, -420]], [[-260, -140], [-140, -140]], [[-260, -800], [260, -800]]], "Boundary": [[-260, 260], [-800, 140]]}