{"Bedroom": {"Size": [-180, -210, 360, 420], "Furnitures": {"Bed": {"Size": [[0, -180, 180, 210]]}, "Wardrobe": {"Size": [[-60, 150, 120, 60]]}}}, "Kitchen": {"Size": [-500, -210, 320, 300], "Furnitures": {"Kitchen_Stove": {"Size": [[-500, -30, 60, 120]]}, "Cupboard": {"Size": [[-380, -60, 50, 150]]}, "Trash_Bin": {"Size": [[-270, 30, 30, 60]]}}}, "Livingroom": {"Size": [-400, -530, 580, 320], "Furnitures": {"Dinner_Table": {"Size": [[-120, -480, 80, 120]]}, "Chair": {"Size": [[-100, -350, 40, 40], [-100, -530, 40, 40], [-170, -440, 40, 40]]}}, "Toilet": {"Size": [60, -480, 120, 90]}, "Bathroom": {"Size": [60, -390, 120, 180]}}, "Doors": {"Entrance": {"Size": [-500, -180, 0, 60]}, "Toilet_Door": {"Size": [60, -465, 0, 60]}, "Bathroom_Door": {"Size": [60, -330, 0, 60]}}, "Walls": [[[-180, 210], [180, 210]], [[-500, 90], [-180, 90]], [[-500, -210], [-400, -210]], [[-400, -530], [180, -530]], [[180, -210], [180, 210]], [[180, -530], [180, -480]], [[-180, 90], [-180, 210]], [[-500, -210], [-500, 90]], [[-400, -530], [-400, -210]]], "Boundary": [[-500, 180], [-530, 210]]}