{"Bedroom": {"Size": [-170, -230, 340, 460], "Furnitures": {"Bed": {"Size": [[-40, -230, 210, 180]]}, "Wardrobe": {"Size": [[90, 110, 60, 120]]}}, "Bathroom": {"Size": [-170, 230, 180, 120]}}, "Kitchen": {"Size": [-990, -110, 320, 340], "Furnitures": {"Kitchen_Stove": {"Size": [[-990, 110, 60, 120]]}, "Cupboard": {"Size": [[-990, -110, 150, 50]]}, "Refrigerator": {"Size": [[-760, 170, 60, 60]]}}}, "Livingroom": {"Size": [-670, -230, 500, 460], "Furnitures": {"Sofa": {"Size": [[-640, -10, 190, 80]]}, "TV": {"Size": [[-595, -230, 100, 60]]}, "Dinner_Table": {"Size": [[-380, -200, 80, 140]]}, "Chair": {"Size": [[-360, -50, 40, 40], [-290, -150, 40, 40], [-430, -150, 40, 40]]}}, "Toilet": {"Size": [-260, 230, 90, 120]}}, "Doors": {"Entrance": {"Size": [-350, 230, 60, 0]}, "Toilet_Door": {"Size": [-245, 230, 60, 0]}, "Bathroom_Door": {"Size": [-110, 230, 60, 0]}}, "Walls": [[[-990, -110], [-670, -110]], [[-670, -230], [170, -230]], [[10, 230], [170, 230]], [[-990, 230], [-260, 230]], [[170, -230], [170, 230]], [[-990, -110], [-990, 230]], [[-670, -230], [-670, -110]]], "Boundary": [[-990, 170], [-230, 350]]}