{"Bedroom": {"Size": [-130, -160, 260, 320], "Furnitures": {"Bed": {"Size": [[-130, -160, 150, 210]]}}}, "Kitchen": {"Size": [570, -160, 320, 200], "Furnitures": {"Kitchen_Stove": {"Size": [[770, -20, 120, 60]]}, "Cupboard": {"Size": [[695, -160, 100, 50]]}, "Refrigerator": {"Size": [[650, -20, 60, 60]]}, "Trash_Bin": {"Size": [[860, -110, 30, 30]]}}}, "Livingroom": {"Size": [130, -160, 440, 320], "Furnitures": {"Sofa": {"Size": [[405, 70, 80, 90]]}, "TV": {"Size": [[185, 75, 40, 80]]}}, "Toilet": {"Size": [310, -280, 90, 120]}, "Bathroom": {"Size": [130, -280, 180, 120]}}, "Doors": {"Entrance": {"Size": [570, 70, 0, 60]}, "Toilet_Door": {"Size": [325, -160, 60, 0]}, "Bathroom_Door": {"Size": [190, -160, 60, 0]}}, "Walls": [[[570, 40], [890, 40]], [[-130, 160], [570, 160]], [[-130, -160], [130, -160]], [[400, -160], [890, -160]], [[-130, -160], [-130, 160]], [[890, -160], [890, 40]], [[570, 40], [570, 160]]], "Boundary": [[-130, 890], [-280, 160]]}