{"Bedroom": {"Size": [-160, -130, 320, 260], "Furnitures": {"Bed": {"Size": [[-30, -80, 180, 210]]}, "Wardrobe": {"Size": [[-160, -10, 60, 80]]}}}, "Kitchen": {"Size": [-160, -650, 320, 200], "Furnitures": {"Kitchen_Stove": {"Size": [[-30, -650, 60, 60]]}, "Cupboard": {"Size": [[-160, -615, 50, 100]]}, "Refrigerator": {"Size": [[100, -650, 60, 60]]}}}, "Livingroom": {"Size": [-160, -450, 440, 320], "Furnitures": {"Sofa": {"Size": [[-20, -250, 80, 90]]}, "TV": {"Size": [[240, -245, 40, 80]]}, "Dinner_Table": {"Size": [[200, -420, 80, 80]]}, "Chair": {"Size": [[150, -400, 40, 40]]}}, "Toilet": {"Size": [-280, -400, 120, 90]}, "Bathroom": {"Size": [-280, -310, 120, 180]}}, "Doors": {"Entrance": {"Size": [-130, 130, 60, 0]}, "Toilet_Door": {"Size": [-160, -385, 0, 60]}, "Bathroom_Door": {"Size": [-160, -250, 0, 60]}}, "Walls": [[[160, -130], [160, 130]], [[160, -650], [160, -450]], [[280, -450], [280, -130]], [[-160, -130], [-160, 130]], [[-160, -650], [-160, -400]], [[-160, 130], [160, 130]], [[160, -130], [280, -130]], [[-160, -650], [160, -650]], [[160, -450], [280, -450]]], "Boundary": [[-280, 280], [-650, 130]]}