{"Bedroom": {"Size": [-160, -160, 320, 320], "Furnitures": {"Bed": {"Size": [[-50, -160, 210, 180]]}, "Nightstand": {"Size": [[120, 20, 40, 40]]}, "Wardrobe": {"Size": [[-40, 100, 100, 60]]}}}, "Kitchen": {"Size": [-920, -160, 260, 320], "Furnitures": {"Kitchen_Stove": {"Size": [[-920, 100, 60, 60]]}, "Cupboard": {"Size": [[-740, 60, 50, 100]]}, "Refrigerator": {"Size": [[-920, -160, 60, 60]]}, "Trash_Bin": {"Size": [[-920, -40, 60, 30]]}}}, "Livingroom": {"Size": [-660, -160, 500, 320], "Furnitures": {"Dinner_Table": {"Size": [[-580, 60, 80, 80]]}, "Chair": {"Size": [[-560, 10, 40, 40]]}, "Sofa": {"Size": [[-310, 60, 90, 80]]}, "TV": {"Size": [[-295, -160, 60, 40]]}}, "Toilet": {"Size": [-480, -280, 90, 120]}, "Bathroom": {"Size": [-660, -280, 180, 120]}}, "Doors": {"Entrance": {"Size": [-190, 160, 60, 0]}, "Toilet_Door": {"Size": [-465, -160, 60, 0]}, "Bathroom_Door": {"Size": [-600, -160, 60, 0]}}, "Walls": [[[-920, 160], [160, 160]], [[-920, -160], [-660, -160]], [[-390, -160], [160, -160]], [[160, -160], [160, 160]], [[-920, -160], [-920, 160]]], "Boundary": [[-920, 160], [-280, 160]]}