{"Bedroom": {"Size": [-200, -190, 400, 380], "Furnitures": {"Bed": {"Size": [[20, -75, 180, 210]]}, "Nightstand": {"Size": [[-20, -75, 40, 40]]}, "Wardrobe": {"Size": [[-200, -15, 120, 60]]}}}, "Kitchen": {"Size": [-200, -550, 280, 360], "Furnitures": {"Kitchen_Stove": {"Size": [[-40, -520, 120, 60]]}, "Cupboard": {"Size": [[-200, -445, 50, 150]]}, "Refrigerator": {"Size": [[20, -280, 60, 60]]}, "Trash_Bin": {"Size": [[50, -370, 30, 30]]}}}, "Livingroom": {"Size": [-200, -1130, 400, 580], "Furnitures": {"Sofa": {"Size": [[-100, -910, 140, 80]]}, "TV": {"Size": [[-70, -1130, 80, 40]]}, "Dinner_Table": {"Size": [[-180, -750, 160, 80]]}, "Chair": {"Size": [[-120, -800, 40, 40], [-120, -660, 40, 40], [-10, -730, 40, 40]]}}, "Toilet": {"Size": [200, -820, 120, 90]}, "Bathroom": {"Size": [200, -730, 120, 180]}}, "Doors": {"Entrance": {"Size": [110, -190, 60, 0]}, "Toilet_Door": {"Size": [200, -805, 0, 60]}, "Bathroom_Door": {"Size": [200, -670, 0, 60]}}, "Walls": [[[-200, -1130], [-200, 190]], [[200, -190], [200, 190]], [[80, -550], [80, -190]], [[200, -1130], [200, -820]], [[-200, 190], [200, 190]], [[80, -550], [200, -550]], [[80, -190], [200, -190]], [[-200, -1130], [200, -1130]]], "Boundary": [[-200, 320], [-1130, 190]]}